<?xml version="1.0" ?>
<innobyte_airlines>

	<airline>
		<id>1</id>
		<name>Airline One</name>
	</airline>

	<city>
		<id>1</id>
		<name>City One</name>
		<population>50000</population>
	</city>
	
	<city>
		<id>2</id>
		<name>City Two</name>
		<population>15000</population>
	</city>
	
	<flight>
		<id>1</id>
		<from_city_id>1</from_city_id>
		<destination_city_id>2</destination_city_id>
		<flight_number>FLIGHTNO01</flight_number>
		<distance>1500</distance>
		<time_interval_start>1570691783</time_interval_start>
		<time_interval_end>1570716983</time_interval_end>
	</flight>

</innobyte_airlines>